LICENSE
MANIFEST.in
README.md
setup.py
django_maced.egg-info/PKG-INFO
django_maced.egg-info/SOURCES.txt
django_maced.egg-info/dependency_links.txt
django_maced.egg-info/top_level.txt
maced/__init__.py
maced/admin.py
maced/apps.py
maced/models.py
maced/tests.py
maced/migrations/__init__.py
maced/static/maced/css/temp.css
maced/static/maced/js/maced.js
maced/templates/maced/container.html
maced/templates/maced/merge_table_row_1.html
maced/templates/maced/modal.html
maced/templates/maced/modal_list.html
maced/templates/maced/inputs/merge_input.html
maced/templates/maced/inputs/merge_panel_input.html
maced/templates/maced/inputs/options.html
maced/templates/maced/inputs/regular_input.html
maced/templatetags/__init__.py
maced/templatetags/pluralize.py
maced/utils/__init__.py
maced/utils/constants.py
maced/utils/errors.py
maced/utils/item_action_helpers.py
maced/utils/item_actions.py
maced/utils/maced_creator.py
maced/utils/misc.py
maced/utils/model_merging.py
maced/views/__init__.py
maced/views/class_based/__init__.py
maced/views/function_based/__init__.py
maced/views/function_based/maced_view.py