Metadata-Version: 1.1
Name: django-maced
Version: 0.4.4
Summary: Django app designed to help with easy database record manipulation/creation through a frontend interface. It is called Maced for Merge Add Clone Edit Delete.
Home-page: https://github.com/Macainian/Django-Maced
Author: Keith Hostetler
Author-email: khostetl@nd.edu
License: MIT License
Platform: UNKNOWN
Classifier: Development Status :: 3 - Alpha
Classifier: License :: OSI Approved :: MIT License
Classifier: Intended Audience :: Developers
Classifier: Operating System :: OS Independent
Classifier: Programming Language :: Python
Classifier: Programming Language :: Python :: 2
Classifier: Programming Language :: Python :: 2.7
Classifier: Topic :: Software Development :: Libraries :: Python Modules
